setup.py
elasticache_pyclient/__init__.py
elasticache_pyclient/memcache_client.py
elasticache_pyclient/repeat_timer.py
elasticache_pyclient_with_stats.egg-info/PKG-INFO
elasticache_pyclient_with_stats.egg-info/SOURCES.txt
elasticache_pyclient_with_stats.egg-info/dependency_links.txt
elasticache_pyclient_with_stats.egg-info/requires.txt
elasticache_pyclient_with_stats.egg-info/top_level.txt
tests/__init__.py
tests/test_memcache_client.py
tests/test_repeat_timer.py