Metadata-Version: 1.0
Name: elasticache-pyclient-with-stats
Version: 2.0
Summary: pythone client for elasticache auto discovery with getting stats function
Home-page: https://github.com/LyuGGang/elasticache_pyclient
Author: LyuGGang
Author-email: me@lyuwonkyung.com
License: LGPL
Keywords: aws,ealsticache
Platform: any
